Metadata-Version: 1.1
Name: PyMea
Version: 0.0.1
Summary: The Maximum Excursion Analysis (MEA) Python C extension module
Home-page: https://github.com/fatfingererr/PyMea
Author: fatfingererr
Author-email: fatfingererr@gmail.com
License: Apache License version 2
Platform: all
Classifier: Operating System :: OS Independent
Classifier: Intended Audience :: Developers
Classifier: Programming Language :: Python
Classifier: Topic :: Software Development :: Libraries
